fludo/__init__.py
fludo/fludo.py
fludo-0.1.dev4.dist-info/LICENSE
fludo-0.1.dev4.dist-info/METADATA
fludo-0.1.dev4.dist-info/WHEEL
fludo-0.1.dev4.dist-info/top_level.txt
fludo-0.1.dev4.dist-info/RECORD
