Metadata-Version: 2.1
Name: fludo
Version: 0.1.dev4
Summary: A lightweight e-liquid calculator package for Python 3.
Home-page: https://github.com/antariandel/fludo
Author: Zsolt Nagy
Author-email: nazsolti@outlook.com
License: UNKNOWN
Platform: UNKNOWN
Classifier: Programming Language :: Python :: 3
Classifier: License :: OSI Approved :: GNU General Public License v3 (GPLv3)
Classifier: Operating System :: OS Independent
